{
  "trainingPhrases": [ {
    "parts": [ {
      "text": "혼자 여러학생을 상담 관리할 수",
      "auto": true
    } ],
    "repeatCount": 1,
    "languageCode": "ko"
  }, {
    "parts": [ {
      "text": "혼자 여러학생을 상담 관리",
      "auto": true
    } ],
    "repeatCount": 1,
    "languageCode": "ko"
  }, {
    "parts": [ {
      "text": "혼자 여러학생을 상담",
      "auto": true
    } ],
    "repeatCount": 1,
    "languageCode": "ko"
  }, {
    "parts": [ {
      "text": "혼자 여러학생",
      "auto": true
    } ],
    "repeatCount": 1,
    "languageCode": "ko"
  }, {
    "parts": [ {
      "text": "혼자 여러학생을 상담",
      "auto": true
    }, {
      "text": " 관리할 ",
      "auto": true
    }, {
      "text": "수",
      "auto": true
    }, {
      "text": " 있나요?",
      "auto": true
    } ],
    "repeatCount": 1,
    "languageCode": "ko"
  } ]
}
