{
  "trainingPhrases": [ {
    "parts": [ {
      "text": "모바일로도 사용",
      "parameterId": "person",
      "auto": true
    } ],
    "repeatCount": 1,
    "languageCode": "ko"
  }, {
    "parts": [ {
      "text": "모바일로도 사용 가능한가",
      "parameterId": "person",
      "auto": true
    } ],
    "repeatCount": 1,
    "languageCode": "ko"
  }, {
    "parts": [ {
      "text": "모바일로도 사용 가능",
      "parameterId": "person",
      "auto": true
    } ],
    "repeatCount": 1,
    "languageCode": "ko"
  }, {
    "parts": [ {
      "text": "모바일",
      "auto": true
    }, {
      "text": "로도 사용 가능한가요?",
      "auto": true
    } ],
    "repeatCount": 1,
    "languageCode": "ko"
  } ]
}
